xia_module_application_gh/__init__.py
xia_module_application_gh/application.py
xia_module_application_gh/foundation.py
xia_module_application_gh/templates/gh-module-application/activate/main.tf
xia_module_application_gh/templates/gh-module-application/activate/variables.tf
xia_module_application_gh/templates/gh-module-application/base/activate.tf
xia_module_application_gh/templates/gh-module-application/base/main.tf
xia_module_application_gh/templates/gh-module-application/config/core/github.yaml
xia_module_application_gh/templates/gh-module-application/module/main.tf
xia_module_application_gh/templates/gh-module-application/module/output.tf
xia_module_application_gh/templates/gh-module-application/module/variables.tf
xia_module_application_gh/templates/gh-module-foundation/base/main.tf
xia_module_application_gh/templates/gh-module-foundation/config/core/github.yaml
xia_module_application_gh/templates/gh-module-foundation/module/main.tf
xia_module_application_gh/templates/gh-module-foundation/module/output.tf
xia_module_application_gh/templates/gh-module-foundation/module/variables.tf
xia_module_application_gh-0.0.21.dist-info/LICENSE
xia_module_application_gh-0.0.21.dist-info/METADATA
xia_module_application_gh-0.0.21.dist-info/WHEEL
xia_module_application_gh-0.0.21.dist-info/top_level.txt
xia_module_application_gh-0.0.21.dist-info/RECORD
