Metadata-Version: 2.1
Name: xia-module-application-gh
Version: 0.0.21
Requires-Python: >=3.9
License-File: LICENSE
Requires-Dist: PyYAML
